gi_scraper/__init__.py
gi_scraper/cache.py
gi_scraper/handler.py
gi_scraper/scraper.py
gi_scraper/stream.py
gi_scraper/util.py
gi_scraper-0.4.6.dist-info/METADATA
gi_scraper-0.4.6.dist-info/WHEEL
gi_scraper-0.4.6.dist-info/top_level.txt
gi_scraper-0.4.6.dist-info/RECORD
