Metadata-Version: 2.1
Name: gi_scraper
Version: 0.4.6
Summary: Google Image Scraper.
Author: Roy6801
Author-email: <mondal6801@gmail.com>
Keywords: python,selenium,web scraping,images,google image scraper,web scraper,image scraping,google images,image scraper,image API,API,automation,data extraction,scraping tool,image downloader,web automation,scraping framework,data scraping,image search,image retrieval
Classifier: Development Status :: 5 - Production/Stable
Classifier: Intended Audience :: Developers
Classifier: Programming Language :: Python :: 3.10
Requires-Dist: selenium
Requires-Dist: webdriver-manager
